[
{
  "name": "date",
  "pattern": "",
  "icon": "fa-calendar",
  "title": "Data e hora da noticia",
  "required": true,
  "type": {
    "view": "date"
  }
},
{
  "name": "hat",
  "title": "Chapéu",
  "required": false,
  "placeholder": "Informe o chapéu",
  "type": {
    "view": "textarea"
  }
},
{
  "name": "title",
  "title": "Título da notícia",
  "required": true,
  "placeholder": "Informe o título",
  "type": {
    "view": "textarea"
  }
},
{
  "name": "support_line",
  "title": "Linha fina",
  "required": true,
  "placeholder": "Informe a linha fina",
  "type": {
    "view": "textarea"
  }
},

{
  "name": "section",
  "title": "Sessão",
  "required": true,
  "type": {
    "view": "select",
    "options": [
      {"name": "Notícia", "id": "news"},
      {"name": "Destaque", "id": "featured"},
      {"name": "Opinião", "id": "opinion"},
      {"name": "Entrevista", "id": "interviews"},
      {"name": "Serviços", "id": "services"},
      {"name": "Variedades", "id": "miscelaneous"},
      {"name": "Impresso", "id": "printed"}
    ]
  }
},
{
  "name": "interviewd",
  "title": "Entrevistado",
  "placeholder": "Informe o nome do entrevistado",
  "required": false,
  "type": {
    "view": "text"
  },
  "need": {
    "field": "section",
    "equal": true,
    "value": "interviews"
  }
},
{
  "name": "menu",
  "title": "Editorias",
  "required": false,
  "type": {
    "view": "select",
    "options": [
      {"id": "sp", "name": "São Paulo"},
      {"id": "brazil", "name": "Brasil"},
      {"id": "world", "name": "Mundo"},
      {"id": "culture", "name": "Cultura"},
      {"id": "sport", "name": "Esportes"},
      {"id": "opinion", "name": "Opinião"},
      {"id": "interviews", "name": "Entrevistas"},
      {"id": "services", "name": "Servicos"}
    ]
  },
    "need": {
    "field": "section",
    "equal": false,
    "value": "printed"
  }
},
{
  "name": "miscelaneous",
  "title": "Variedades",
  "required": false,
  "type": {
    "view": "select",
    "options": [
      {"name": "Horóscopo", "id": "horoscope"},
      {"name": "Receita", "id": "recipe"},
      {"name": "Agenda Cultural", "id": "cultural-agenda"}
    ]
  },
    "need": {
    "field": "section",
    "equal": true,
    "value": "miscelaneous"
  }
},
{
  "name": "service",
  "title": "Serviços",
  "required": false,
  "type": {
    "view": "select",
    "options": [
      {"name": "Nossa Saúde", "id": "our-health"},
      {"name": "Nosso Direito", "id": "our-rights"},
      {"name": "Mural do Leitor", "id": "reader-board"}
    ]
  },
    "need": {
    "field": "section",
    "equal": true,
    "value": "services"
  }
},
{
  "name": "images_hd",
  "pattern": "",
  "icon": "fa-picture-o",
  "title": "Imagem de Capa",
  "required": true,
  "type": {
    "view": "cover"
  },
  "need": {
    "field": "section",
    "equal": false,
    "value": "opinion"
  }
},
{
  "name": "tags",
  "pattern": "",
  "icon": "fa-tags",
  "title": "Tags",
  "required": false,
  "type": {
    "view": "tagging"
  }
}
]
